{"width":4,"height":5,"pins":{"19434":{"x":0,"y":5,"c":"blue","readonly":false,"ID":19434},"39283":{"x":1,"y":0,"c":"white","readonly":false,"ID":39283},"40120":{"x":4,"y":2,"c":"white","readonly":false,"ID":40120},"43873":{"x":4,"y":0,"c":"blue","readonly":false,"ID":43873},"51450":{"x":2,"y":5,"c":"white","readonly":false,"ID":51450},"99922":{"x":1,"y":3,"c":"white","readonly":false,"ID":99922}},"lines":{"30123":{"ID":30123,"c":"white","pos":[[1,3],[0,3],[0,4],[1,4],[2,4],[3,4],[4,4],[4,5],[3,5],[2,5]]},"93295":{"ID":93295,"c":"white","pos":[[1,0],[0,0],[0,1],[0,2],[1,2],[2,2],[3,2],[3,1],[4,1],[4,2]]}}}