{
  "width": 6,
  "height": 8,
  "pads": [
    {
      "pos": [
        3,
        0
      ],
      "ID": 7198
    },
    {
      "pos": [
        4,
        4
      ],
      "ID": 7513
    },
    {
      "pos": [
        1,
        1
      ],
      "ID": 17798
    },
    {
      "pos": [
        3,
        4
      ],
      "ID": 43773
    },
    {
      "pos": [
        6,
        3
      ],
      "ID": 52122
    },
    {
      "pos": [
        3,
        3
      ],
      "ID": 58115
    },
    {
      "pos": [
        5,
        3
      ],
      "ID": 74251
    },
    {
      "pos": [
        4,
        5
      ],
      "ID": 79517
    },
    {
      "pos": [
        0,
        3
      ],
      "ID": 87299
    },
    {
      "pos": [
        3,
        5
      ],
      "ID": 92132
    }
  ],
  "terminals": [
    {
      "pos": [
        3,
        8
      ],
      "color": "green",
      "ID": 56381
    },
    {
      "pos": [
        5,
        1
      ],
      "color": "green",
      "ID": 65024
    },
    {
      "pos": [
        1,
        8
      ],
      "color": "blue",
      "ID": 81623
    },
    {
      "pos": [
        5,
        8
      ],
      "color": "blue",
      "ID": 93147
    }
  ],
  "lines": [
    {
      "ID": 19064,
      "layer":0,
      "pos": [
        [
          3,
          0
        ],
        [
          3,
          1
        ],
        [
          2,
          2
        ],
        [
          2,
          3
        ],
        [
          3,
          3
        ]
      ]
    },
    {
      "ID": 34154,
      "layer":0,
      "pos": [
        [
          4,
          4
        ],
        [
          5,
          4
        ],
        [
          5,
          5
        ],
        [
          4,
          5
        ]
      ]
    },
    {
      "ID": 37065,
      "layer":0,
      "pos": [
        [
          3,
          3
        ],
        [
          3,
          4
        ]
      ]
    },
    {
      "ID": 74822,
      "layer":0,
      "pos": [
        [
          3,
          5
        ],
        [
          2,
          5
        ],
        [
          1,
          5
        ],
        [
          0,
          5
        ],
        [
          0,
          4
        ],
        [
          0,
          3
        ]
      ]
    },
    {
      "ID": 76867,
      "layer":0,
      "pos": [
        [
          3,
          4
        ],
        [
          2,
          4
        ],
        [
          1,
          4
        ],
        [
          1,
          3
        ],
        [
          1,
          2
        ],
        [
          1,
          1
        ]
      ]
    },
    {
      "ID": 98247,
      "layer":0,
      "pos": [
        [
          5,
          3
        ],
        [
          6,
          3
        ]
      ]
    }
  ]
}
